graia/creart/__init__.py
graia/creart/broadcast.py
graia/creart/saya.py
graia/creart/scheduler.py
creart_graia-0.1.7.dist-info/WHEEL
creart_graia-0.1.7.dist-info/METADATA
creart_graia-0.1.7.dist-info/licenses/LICENSE
creart_graia-0.1.7.dist-info/RECORD
