Metadata-Version: 2.1
Name: creart-graia
Version: 0.1.7
License: MIT
Author-email: GreyElaina <GreyElaina@outlook.com>
Requires-Python: >=3.8
Requires-Dist: creart<0.3.0,>=0.1.0
